featurizerai/__init__.py
featurizerai/api.py
tests/__init__.py
tests/test.py
featurizerai-0.2.dist-info/METADATA
featurizerai-0.2.dist-info/WHEEL
featurizerai-0.2.dist-info/top_level.txt
featurizerai-0.2.dist-info/RECORD
