Metadata-Version: 2.1
Name: featurizerai
Version: 0.2
Author: Featurizer AI
License: MIT
Requires-Dist: requests
